aksara/__init__.py
aksara/__main__.py
aksara/conllu.py
aksara/dependency_parser.py
aksara/lemmatizer.py
aksara/morphological_analyzer.py
aksara/morphological_feature.py
aksara/pos_tagger.py
aksara/_nlp_internal/__init__.py
aksara/_nlp_internal/analyzer.py
aksara/_nlp_internal/core.py
aksara/_nlp_internal/disambiguator.py
aksara/_nlp_internal/formatter.py
aksara/_nlp_internal/parser.py
aksara/_nlp_internal/tokenizer.py
aksara/_nlp_internal/bin/__init__.py
aksara/_nlp_internal/bin/_get_foma_script_path.py
aksara/_nlp_internal/bin/aksara@v1.2.0.bin
aksara/_nlp_internal/dependency_parsing/__init__.py
aksara/_nlp_internal/dependency_parsing/core.py
aksara/_nlp_internal/dependency_parsing/model_proxy.py
aksara/_nlp_internal/dependency_parsing/alphabets/character.json
aksara/_nlp_internal/dependency_parsing/alphabets/pos.json
aksara/_nlp_internal/dependency_parsing/alphabets/type.json
aksara/_nlp_internal/dependency_parsing/alphabets/word.json
aksara/_nlp_internal/dependency_parsing/neuronlp2/__init__.py
aksara/_nlp_internal/dependency_parsing/neuronlp2/utils.py
aksara/_nlp_internal/dependency_parsing/neuronlp2/io/__init__.py
aksara/_nlp_internal/dependency_parsing/neuronlp2/io/alphabet.py
aksara/_nlp_internal/dependency_parsing/neuronlp2/io/conllx_data.py
aksara/_nlp_internal/dependency_parsing/neuronlp2/io/instance.py
aksara/_nlp_internal/dependency_parsing/neuronlp2/io/logger.py
aksara/_nlp_internal/dependency_parsing/neuronlp2/io/reader.py
aksara/_nlp_internal/dependency_parsing/neuronlp2/io/utils.py
aksara/_nlp_internal/dependency_parsing/neuronlp2/io/writer.py
aksara/_nlp_internal/dependency_parsing/neuronlp2/io_multi/__init__.py
aksara/_nlp_internal/dependency_parsing/neuronlp2/io_multi/lang_id.py
aksara/_nlp_internal/dependency_parsing/neuronlp2/io_multi/multi_vocab.py
aksara/_nlp_internal/dependency_parsing/neuronlp2/models/__init__.py
aksara/_nlp_internal/dependency_parsing/neuronlp2/models/parsing.py
aksara-1.14.dist-info/LICENSE
aksara-1.14.dist-info/METADATA
aksara-1.14.dist-info/WHEEL
aksara-1.14.dist-info/top_level.txt
aksara-1.14.dist-info/RECORD
