Metadata-Version: 2.1
Name: aksara
Version: 1.14
Summary: Aksara is an Indonesian NLP tool that conforms to the Universal Dependencies (UD) v2
Project-URL: Source Code, https://github.com/ir-nlp-csui/aksara
Project-URL: Issue Tracker, https://github.com/ir-nlp-csui/aksara/issues
License-File: LICENSE
Requires-Dist: tqdm (<5,>=4.65.0)
Requires-Dist: scikit-learn (<2,>=1.2.2)
Requires-Dist: numpy (<2,>=1.22.4)
Requires-Dist: pandas (<2,>=1.4.4)
Requires-Dist: seaborn (<1,>=0.12.2)
Requires-Dist: nltk (<4,>=3.8.1)
Requires-Dist: torch (<2.1.0,>=1.13.1)
Requires-Dist: gensim (<5,>=4.3.1)
Requires-Dist: gdown (<5,>=4.6.4)
Requires-Dist: igraph (<1,>=0.10.4)
Requires-Dist: plotly (<5.15,>=5.14.1)
Requires-Dist: matplotlib (<4,>=3.7.1)
Requires-Dist: kaleido (==0.2.1) ; platform_system != "Windows"
Requires-Dist: kaleido (==0.1.0.post1) ; platform_system == "Windows"
